README.md
setup.py
seeing/__init__.py
seeing.egg-info/PKG-INFO
seeing.egg-info/SOURCES.txt
seeing.egg-info/dependency_links.txt
seeing.egg-info/entry_points.txt
seeing.egg-info/top_level.txt