Metadata-Version: 2.1
Name: seeing
Version: 0.1.6
Summary: Monitor & auto execute single script(go py c) after modify.
Home-page: https://github.com/toyourheart163/seeing
Author: Mikele
Author-email: blive200@gmail.com
License: UNKNOWN
Platform: UNKNOWN
Classifier: Programming Language :: Python :: 3
Classifier: License :: OSI Approved :: MIT License
Classifier: Operating System :: OS Independent
Requires-Python: >=3.6
